incendium/__about__.pyi
incendium/__init__.pyi
incendium/constants.pyi
incendium/dataset.pyi
incendium/date.pyi
incendium/db.pyi
incendium/exceptions.pyi
incendium/gui.pyi
incendium/net.pyi
incendium/py.typed
incendium/tag.pyi
incendium/time.pyi
incendium/helper/__init__.pyi
incendium/helper/py.typed
incendium/helper/types.pyi
incendium/vision/__init__.pyi
incendium/vision/gui.pyi
incendium/vision/nav.pyi
incendium/vision/py.typed
incendium/vision/user.pyi
incendium_stubs-2025.12.0.dist-info/METADATA
incendium_stubs-2025.12.0.dist-info/WHEEL
incendium_stubs-2025.12.0.dist-info/top_level.txt
incendium_stubs-2025.12.0.dist-info/RECORD
