Metadata-Version: 2.4
Name: incendium-stubs
Version: 2025.12.0
Summary: incendium stubs package
Author-email: César Román <cesar@coatl.dev>
License-Expression: MIT
Project-URL: Funding, https://github.com/sponsors/cesarcoatl
Project-URL: Source, https://github.com/ignition-devs/incendium
Project-URL: Tracker, https://github.com/ignition-devs/incendium/issues
Keywords: hmi,ignition,inductive automation,scada
Classifier: Development Status :: 5 - Production/Stable
Classifier: Intended Audience :: Developers
Classifier: Intended Audience :: Information Technology
Classifier: Intended Audience :: Manufacturing
Classifier: Operating System :: MacOS :: MacOS X
Classifier: Operating System :: Microsoft :: Windows
Classifier: Operating System :: POSIX :: Linux
Classifier: Programming Language :: Python
Classifier: Programming Language :: Python :: 3 :: Only
Classifier: Programming Language :: Python :: 3.9
Classifier: Programming Language :: Python :: 3.10
Classifier: Programming Language :: Python :: 3.11
Classifier: Programming Language :: Python :: 3.12
Classifier: Typing :: Stubs Only
Classifier: Typing :: Typed
Requires-Python: <3.13,>=3.9
Requires-Dist: ignition-api-stubs>=8.3
